setup.py
vulcanize/__init__.py
vulcanize/__main__.py
vulcanize/assembler.py
vulcanize/errors.py
vulcanize/importer.py
vulcanize/pipeline.py
vulcanize/server.py
vulcanize.egg-info/PKG-INFO
vulcanize.egg-info/SOURCES.txt
vulcanize.egg-info/dependency_links.txt
vulcanize.egg-info/entry_points.txt
vulcanize.egg-info/requires.txt
vulcanize.egg-info/top_level.txt