Metadata-Version: 1.1
Name: vulcanize
Version: 0.2
Summary: Vulcanizes HTML files that use Polymer
Home-page: https://github.com/bslatkin/pyvulcanize
Author: Brett Slatkin
Author-email: brett@haxor.com
License: UNKNOWN
Keywords: polymer
Platform: UNKNOWN
Classifier: Programming Language :: Python
Classifier: Programming Language :: Python :: 2.7
Classifier: Development Status :: 5 - Production/Stable
Classifier: Environment :: Web Environment
Classifier: Intended Audience :: Developers
Classifier: License :: OSI Approved :: Apache Software License
Classifier: Operating System :: OS Independent
Classifier: Topic :: Software Development :: Libraries :: Python Modules
Classifier: Topic :: Text Processing :: Markup :: HTML
